{"expand":"renderedFields,names,schema,transitions,operations,editmeta,changelog","id":"126265","self":"http://jira.codehaus.org/rest/api/latest/issue/126265","key":"PLXCOMP-176","fields":{"progress":{"progress":0,"total":0},"summary":"plexus-archiver used in maven creates tar files with junk padding that confuse some tar programs","timetracking":{},"issuetype":{"self":"http://jira.codehaus.org/rest/api/2/issuetype/1","id":"1","description":"A problem which impairs or prevents the functions of the product.","iconUrl":"http://jira.codehaus.org/images/icons/issuetypes/bug.png","name":"Bug","subtask":false},"customfield_10110":null,"votes":{"self":"http://jira.codehaus.org/rest/api/2/issue/PLXCOMP-176/votes","votes":0,"hasVoted":false},"resolution":{"self":"http://jira.codehaus.org/rest/api/2/resolution/1","id":"1","description":"A fix for this issue is checked into the tree and tested.","name":"Fixed"},"fixVersions":[{"self":"http://jira.codehaus.org/rest/api/2/version/18270","id":"18270","name":"plexus-archiver-2.0.2","archived":false,"released":true,"releaseDate":"2012-01-14"}],"resolutiondate":"2012-01-12T11:30:48.892-0600","customfield_10210":"0.0","timespent":null,"reporter":{"self":"http://jira.codehaus.org/rest/api/2/user?username=alexlehm","name":"alexlehm","emailAddress":"alexlehm@gmail.com","avatarUrls":{"16x16":"http://jira.codehaus.org/secure/useravatar?size=xsmall&avatarId=10232","24x24":"http://jira.codehaus.org/secure/useravatar?size=small&avatarId=10232","32x32":"http://jira.codehaus.org/secure/useravatar?size=medium&avatarId=10232","48x48":"http://jira.codehaus.org/secure/useravatar?avatarId=10232"},"displayName":"Alexander Lehmann","active":true},"aggregatetimeoriginalestimate":null,"customfield_10161":["alexlehm(alexlehm)","krosenvold(krosenvold)"],"customfield_10160":null,"updated":"2012-01-12T11:30:49.044-0600","created":"2011-06-07T17:15:30.058-0500","description":"The issue is present in versions 1.1 and 1.2 as well.\r\n\r\nthe tar function creates tar files that are padded at the end with junk data from previous data in the archive. this is an issue that was present in the ant tar function was well and was fixed there about 2 years ago (ant >=1.8.0).\r\n\r\nTo fix this, you could either resync the tar implementation from current ant or apply the path individually. The patch is listed here \r\n\r\nhttps://fisheye6.atlassian.com/browse/ant/core/trunk/src/main/org/apache/tools/tar/TarBuffer.java?r2=789556&r1=597087\r\n\r\n","priority":{"self":"http://jira.codehaus.org/rest/api/2/priority/3","iconUrl":"http://jira.codehaus.org/images/icons/priorities/major.png","name":"Major","id":"3"},"duedate":null,"issuelinks":[],"customfield_10163":"94867200","watches":{"self":"http://jira.codehaus.org/rest/api/2/issue/PLXCOMP-176/watchers","watchCount":0,"isWatching":false},"worklog":{"startAt":0,"maxResults":20,"total":0,"worklogs":[]},"subtasks":[],"status":{"self":"http://jira.codehaus.org/rest/api/2/status/6","description":"The issue is considered finished, the resolution is correct. Issues which are closed can be reopened.","iconUrl":"http://jira.codehaus.org/images/icons/statuses/closed.png","name":"Closed","id":"6"},"customfield_10090":null,"labels":[],"workratio":-1,"assignee":{"self":"http://jira.codehaus.org/rest/api/2/user?username=krosenvold","name":"krosenvold","emailAddress":"krosenvold@apache.org","avatarUrls":{"16x16":"http://jira.codehaus.org/secure/useravatar?size=xsmall&ownerId=krosenvold&avatarId=11127","24x24":"http://jira.codehaus.org/secure/useravatar?size=small&ownerId=krosenvold&avatarId=11127","32x32":"http://jira.codehaus.org/secure/useravatar?size=medium&ownerId=krosenvold&avatarId=11127","48x48":"http://jira.codehaus.org/secure/useravatar?ownerId=krosenvold&avatarId=11127"},"displayName":"Kristian Rosenvold","active":true},"attachment":[],"customfield_10221":null,"customfield_10220":null,"customfield_10200":null,"aggregatetimeestimate":null,"customfield_10190":null,"project":{"self":"http://jira.codehaus.org/rest/api/2/project/11440","id":"11440","key":"PLXCOMP","name":"Plexus Components","avatarUrls":{"16x16":"http://jira.codehaus.org/secure/projectavatar?size=xsmall&pid=11440&avatarId=10011","24x24":"http://jira.codehaus.org/secure/projectavatar?size=small&pid=11440&avatarId=10011","32x32":"http://jira.codehaus.org/secure/projectavatar?size=medium&pid=11440&avatarId=10011","48x48":"http://jira.codehaus.org/secure/projectavatar?pid=11440&avatarId=10011"},"projectCategory":{"self":"http://jira.codehaus.org/rest/api/2/projectCategory/10003","id":"10003","description":"various containers","name":"containers"}},"versions":[{"self":"http://jira.codehaus.org/rest/api/2/version/17284","id":"17284","description":"","name":"plexus-archiver-1.0","archived":false,"released":true,"releaseDate":"2010-04-25"},{"self":"http://jira.codehaus.org/rest/api/2/version/17283","id":"17283","description":"","name":"plexus-archiver-1.1","archived":false,"released":true,"releaseDate":"2010-09-28"},{"self":"http://jira.codehaus.org/rest/api/2/version/17282","id":"17282","description":"","name":"plexus-archiver-1.2","archived":false,"released":true,"releaseDate":"2010-10-09"}],"customfield_10170":null,"environment":"windows vista java 1.6.024 plexus-archiver 1.0 maven 3.0.3\r\n","timeestimate":null,"customfield_10130":null,"aggregateprogress":{"progress":0,"total":0},"lastViewed":null,"components":[{"self":"http://jira.codehaus.org/rest/api/2/component/12540","id":"12540","name":"plexus-archiver"}],"comment":{"startAt":0,"maxResults":2,"total":2,"comments":[{"self":"http://jira.codehaus.org/rest/api/2/issue/126265/comment/269761","id":"269761","author":{"self":"http://jira.codehaus.org/rest/api/2/user?username=alexlehm","name":"alexlehm","emailAddress":"alexlehm@gmail.com","avatarUrls":{"16x16":"http://jira.codehaus.org/secure/useravatar?size=xsmall&avatarId=10232","24x24":"http://jira.codehaus.org/secure/useravatar?size=small&avatarId=10232","32x32":"http://jira.codehaus.org/secure/useravatar?size=medium&avatarId=10232","48x48":"http://jira.codehaus.org/secure/useravatar?avatarId=10232"},"displayName":"Alexander Lehmann","active":true},"body":"the bug report for ant is the following:\r\n\r\nhttps://issues.apache.org/bugzilla/show_bug.cgi?id=47421\r\n\r\n","updateAuthor":{"self":"http://jira.codehaus.org/rest/api/2/user?username=alexlehm","name":"alexlehm","emailAddress":"alexlehm@gmail.com","avatarUrls":{"16x16":"http://jira.codehaus.org/secure/useravatar?size=xsmall&avatarId=10232","24x24":"http://jira.codehaus.org/secure/useravatar?size=small&avatarId=10232","32x32":"http://jira.codehaus.org/secure/useravatar?size=medium&avatarId=10232","48x48":"http://jira.codehaus.org/secure/useravatar?avatarId=10232"},"displayName":"Alexander Lehmann","active":true},"created":"2011-06-07T17:16:50.687-0500","updated":"2011-06-07T17:16:50.687-0500"},{"self":"http://jira.codehaus.org/rest/api/2/issue/126265/comment/288145","id":"288145","author":{"self":"http://jira.codehaus.org/rest/api/2/user?username=krosenvold","name":"krosenvold","emailAddress":"krosenvold@apache.org","avatarUrls":{"16x16":"http://jira.codehaus.org/secure/useravatar?size=xsmall&ownerId=krosenvold&avatarId=11127","24x24":"http://jira.codehaus.org/secure/useravatar?size=small&ownerId=krosenvold&avatarId=11127","32x32":"http://jira.codehaus.org/secure/useravatar?size=medium&ownerId=krosenvold&avatarId=11127","48x48":"http://jira.codehaus.org/secure/useravatar?ownerId=krosenvold&avatarId=11127"},"displayName":"Kristian Rosenvold","active":true},"body":"Applied fix from ant in 28fc404cc38d3d515e0ffe6c2475d5e7d345c470","updateAuthor":{"self":"http://jira.codehaus.org/rest/api/2/user?username=krosenvold","name":"krosenvold","emailAddress":"krosenvold@apache.org","avatarUrls":{"16x16":"http://jira.codehaus.org/secure/useravatar?size=xsmall&ownerId=krosenvold&avatarId=11127","24x24":"http://jira.codehaus.org/secure/useravatar?size=small&ownerId=krosenvold&avatarId=11127","32x32":"http://jira.codehaus.org/secure/useravatar?size=medium&ownerId=krosenvold&avatarId=11127","48x48":"http://jira.codehaus.org/secure/useravatar?ownerId=krosenvold&avatarId=11127"},"displayName":"Kristian Rosenvold","active":true},"created":"2012-01-12T11:30:48.989-0600","updated":"2012-01-12T11:30:48.989-0600"}]},"timeoriginalestimate":null,"aggregatetimespent":null}}